ingest/__init__.py
ingest/annotations.py
ingest/cell_metadata.py
ingest/cli_parser.py
ingest/clusters.py
ingest/config.py
ingest/ingest_files.py
ingest/ingest_pipeline.py
ingest/loom.py
ingest/make_toy_data.py
ingest/mongo_connection.py
ingest/monitor.py
ingest/parallel_processing_ingest_dense_matrix.py
ingest/subsample.py
ingest/zarr_ingest.py
ingest/expression_files/__init__.py
ingest/expression_files/dense_ingestor.py
ingest/expression_files/expression_files.py
ingest/expression_files/mtx.py
ingest/genomes/__init__.py
ingest/genomes/fetch_upstream_assemblies.py
ingest/genomes/genome_annotation_metadata.py
ingest/genomes/genome_annotations.py
ingest/genomes/genome_assemblies.py
ingest/genomes/genomes_pipeline.py
ingest/genomes/utils.py
ingest/monitoring/__init__.py
ingest/monitoring/metrics_service.py
ingest/monitoring/mixpanel_log.py
ingest/validation/__init__.py
ingest/validation/validate_metadata.py
scp_ingest_pipeline-1.12.2.dist-info/LICENSE
scp_ingest_pipeline-1.12.2.dist-info/METADATA
scp_ingest_pipeline-1.12.2.dist-info/WHEEL
scp_ingest_pipeline-1.12.2.dist-info/top_level.txt
scp_ingest_pipeline-1.12.2.dist-info/RECORD
