Metadata-Version: 2.1
Name: scp-ingest-pipeline
Version: 1.12.2
Summary: ETL pipeline for single-cell RNA-seq data
Home-page: https://github.com/broadinstitute/scp-ingest-pipeline
Author: Single Cell Portal team
Author-email: scp-support@broadinstitute.zendesk.com
License: UNKNOWN
Platform: UNKNOWN
Classifier: Development Status :: 5 - Production/Stable
Classifier: License :: OSI Approved :: BSD License
Classifier: Topic :: Scientific/Engineering :: Bio-Informatics
Classifier: Programming Language :: Python :: 3.7
Requires-Python: >=3.7
License-File: LICENSE
Requires-Dist: google-cloud-storage
Requires-Dist: google-cloud-bigquery
Requires-Dist: requests
Requires-Dist: numpy
Requires-Dist: scipy
Requires-Dist: jsonschema
Requires-Dist: pandas
Requires-Dist: pandocfilters
Requires-Dist: colorama
Requires-Dist: dataclasses
Requires-Dist: mypy-extensions
Requires-Dist: pymongo
Requires-Dist: loompy
Requires-Dist: backoff
Requires-Dist: opencensus
Requires-Dist: opencensus-context
Requires-Dist: opencensus-ext-stackdriver
Requires-Dist: google-cloud-trace
Requires-Dist: grpcio
Requires-Dist: sentry-sdk
